agp_mcp/__init__.py
agp_mcp/client.py
agp_mcp/common.py
agp_mcp/server.py
agp_mcp-0.1.5.dist-info/METADATA
agp_mcp-0.1.5.dist-info/WHEEL
agp_mcp-0.1.5.dist-info/RECORD
