Metadata-Version: 2.4
Name: agp-mcp
Version: 0.1.5
Summary: Model Context Protocol with AGP as transport
License-Expression: Apache-2.0
Classifier: Development Status :: 3 - Alpha
Classifier: Intended Audience :: Developers
Classifier: Programming Language :: Python :: 3.10
Classifier: Programming Language :: Python :: 3.11
Classifier: Programming Language :: Python :: 3.12
Classifier: Programming Language :: Python :: 3.13
Classifier: Topic :: Software Development :: Libraries
Requires-Python: <4.0,>=3.10
Requires-Dist: agp-bindings>=0.3.5
Requires-Dist: anyio>=4.5
Requires-Dist: mcp==1.6.0
